invoke_plugin_for_pylint/__init__.py
invoke_plugin_for_pylint/_plugin.py
invoke_plugin_for_pylint-5.0.0.dist-info/licenses/LICENSE
invoke_plugin_for_pylint-5.0.0.dist-info/METADATA
invoke_plugin_for_pylint-5.0.0.dist-info/WHEEL
invoke_plugin_for_pylint-5.0.0.dist-info/top_level.txt
invoke_plugin_for_pylint-5.0.0.dist-info/RECORD
