Metadata-Version: 2.4
Name: invoke-plugin-for-pylint
Version: 5.0.0
Summary: Pylint plugin which disables checks for proper integration with invoke
Author-email: Kai Harder <kai.harder@sap.com>
License-Expression: Apache-2.0
Project-URL: Changelog, https://github.com/SAP/invoke-plugin-for-pylint/blob/main/CHANGELOG.md
Project-URL: Issue Tracker, https://github.com/SAP/invoke-plugin-for-pylint/issues
Keywords: pylint,invoke,plugin,inv,linter
Classifier: Development Status :: 5 - Production/Stable
Classifier: Environment :: Plugins
Classifier: Intended Audience :: Developers
Classifier: Natural Language :: English
Classifier: Operating System :: OS Independent
Classifier: Programming Language :: Python :: 3
Classifier: Programming Language :: Python :: 3 :: Only
Classifier: Programming Language :: Python :: 3.10
Classifier: Programming Language :: Python :: 3.11
Classifier: Programming Language :: Python :: 3.12
Classifier: Programming Language :: Python :: 3.13
Classifier: Programming Language :: Python :: 3.14
Classifier: Topic :: Software Development :: Quality Assurance
Classifier: Typing :: Typed
Requires-Python: <4,>=3.10
License-File: LICENSE
Requires-Dist: invoke~=2.0
Requires-Dist: pylint<5,>=3.0
Requires-Dist: astroid<5,>=3.0
Dynamic: license-file
